fractifhttp/__init__.py
fractifhttp/client.py
fractifhttp/logger.py
fractifhttp/regex_helper.py
fractifhttp/url.py
fractif_http-0.0.7.dist-info/METADATA
fractif_http-0.0.7.dist-info/WHEEL
fractif_http-0.0.7.dist-info/top_level.txt
fractif_http-0.0.7.dist-info/RECORD
