Metadata-Version: 2.1
Name: fractif-http
Version: 0.0.7
Summary: Simple, yet elegant, HTTP library. As like as Requests. Actually, it is based on requests package...
Home-page: https://github.com/Fractif/fractif-http
Author: Tom LARGE
Author-email: tom@fractif.com
License: MIT
Keywords: http
Platform: UNKNOWN
Classifier: Development Status :: 3 - Alpha
Classifier: Intended Audience :: Developers
Classifier: License :: OSI Approved :: MIT License
Classifier: Programming Language :: Python :: 3
Requires-Dist: requests
Requires-Dist: bs4
Requires-Dist: user-agent
Requires-Dist: coloredlogs
